[
  {
    "timestamp": "2025-11-05T19:41:05.139704",
    "tool_name": "document_reader",
    "input": {
      "doc_id": "INV-001"
    },
    "output": "{'found': True, 'doc_type': 'invoice'}"
  },
  {
    "timestamp": "2025-11-05T19:41:10.013507",
    "tool_name": "calculator",
    "input": {
      "expression": "20000 + 2000"
    },
    "output": "{'result': 22000}"
  },
  {
    "timestamp": "2025-11-05T19:41:22.741170",
    "tool_name": "calculator",
    "input": {
      "expression": "0.15 * 22000"
    },
    "output": "{'result': 3300.0}"
  },
  {
    "timestamp": "2025-11-05T19:41:41.217748",
    "tool_name": "document_search",
    "input": {
      "query": "invoices",
      "search_type": "type",
      "doc_type": "invoice",
      "min_amount": null,
      "max_amount": null,
      "comparison": null,
      "amount": null
    },
    "output": "{'results_count': 3}"
  }
]